Workbook

Sheet Employee Master
A1: EMPLOYEE MASTER
A2: Single source of truth — all departments | AutoEra Dealership HR System
A3: Emp ID | B3: Full Name | C3: Department | D3: Designation | E3: Reporting Manager | F3: Date of Joining | G3: Employment Type | H3: Location/Branch | I3: Contact No | J3: Email | K3: Date of Birth | L3: Tenure (Years) | M3: Status | N3: CTC (Annual ₹) | O3: Emergency Contact
A4: AE-001 | B4: Arun Kumar S | C4: Sales | D4: Sales Executive | E4: Manikandan R | F4: 2023-04-10 | G4: Permanent | H4: Valasaravakkam | I4: 9840012345 | J4: arun.k@dealer.com | K4: 1994-05-12 | L4: =DATEDIF(F4,TODAY(),"y")&" yrs "&DATEDIF(F4,TODAY(),"ym")&" mo" -> 3 yrs 2 mo | M4: Active | N4: 360000 | O4: 9840099001
A5: AE-002 | B5: Priya Venkatesh | C5: Service | D5: Service Advisor | E5: Rajesh N | F5: 2022-11-01 | G5: Permanent | H5: Valasaravakkam | I5: 9840012346 | J5: priya.v@dealer.com | K5: 1996-08-23 | L5: =DATEDIF(F5,TODAY(),"y")&" yrs "&DATEDIF(F5,TODAY(),"ym")&" mo" -> 3 yrs 8 mo | M5: Active | N5: 384000 | O5: 9840099002
A6: AE-003 | B6: Manikandan R | C6: Sales | D6: Sales Manager | E6: GM Sales | F6: 2020-06-15 | G6: Permanent | H6: Valasaravakkam | I6: 9840012347 | J6: mani.r@dealer.com | K6: 1988-02-17 | L6: =DATEDIF(F6,TODAY(),"y")&" yrs "&DATEDIF(F6,TODAY(),"ym")&" mo" -> 6 yrs 0 mo | M6: Active | N6: 720000 | O6: 9840099003
A7: AE-004 | B7: Suresh Babu | C7: Bodyshop | D7: Painter | E7: Rajesh N | F7: 2021-09-20 | G7: Permanent | H7: Valasaravakkam | I7: 9840012348 | J7: suresh.b@dealer.com | K7: 1991-12-01 | L7: =DATEDIF(F7,TODAY(),"y")&" yrs "&DATEDIF(F7,TODAY(),"ym")&" mo" -> 4 yrs 9 mo | M7: Active | N7: 300000 | O7: 9840099004
A8: AE-005 | B8: Lakshmi Narayanan | C8: Spare Parts | D8: Parts Executive | E8: Rajesh N | F8: 2023-01-05 | G8: Permanent | H8: Valasaravakkam | I8: 9840012349 | J8: lakshmi.n@dealer.com | K8: 1995-03-30 | L8: =DATEDIF(F8,TODAY(),"y")&" yrs "&DATEDIF(F8,TODAY(),"ym")&" mo" -> 3 yrs 5 mo | M8: Active | N8: 288000 | O8: 9840099005
A9: AE-006 | B9: Rajesh N | C9: Service | D9: Service Manager | E9: COO | F9: 2019-03-11 | G9: Permanent | H9: Valasaravakkam | I9: 9840012350 | J9: rajesh.n@dealer.com | K9: 1985-07-08 | L9: =DATEDIF(F9,TODAY(),"y")&" yrs "&DATEDIF(F9,TODAY(),"ym")&" mo" -> 7 yrs 3 mo | M9: Active | N9: 840000 | O9: 9840099006
A10: AE-007 | B10: Divya Shree | C10: HR & Admin | D10: HR Generalist | E10: CEO | F10: 2022-02-14 | G10: Permanent | H10: Valasaravakkam | I10: 9840012351 | J10: divya.s@dealer.com | K10: 1993-10-19 | L10: =DATEDIF(F10,TODAY(),"y")&" yrs "&DATEDIF(F10,TODAY(),"ym")&" mo" -> 4 yrs 4 mo | M10: Active | N10: 420000 | O10: 9840099007
A11: AE-008 | B11: Karthik Raja | C11: Sales | D11: Sales Executive | E11: Manikandan R | F11: 2024-06-01 | G11: Probation | H11: Valasaravakkam | I11: 9840012352 | J11: karthik.r@dealer.com | K11: 1998-01-25 | L11: =DATEDIF(F11,TODAY(),"y")&" yrs "&DATEDIF(F11,TODAY(),"ym")&" mo" -> 2 yrs 1 mo | M11: Active | N11: 300000 | O11: 9840099008
A12: AE-009 | B12: Vignesh Kumar | C12: Technician | D12: Senior Technician | E12: Rajesh N | F12: 2021-01-18 | G12: Permanent | H12: Valasaravakkam | I12: 9840012353 | J12: vignesh.k@dealer.com | K12: 1990-04-14 | L12: =DATEDIF(F12,TODAY(),"y")&" yrs "&DATEDIF(F12,TODAY(),"ym")&" mo" -> 5 yrs 5 mo | M12: Resigned | N12: 336000 | O12: 9840099009
A13: AE-010 | B13: Anitha R | C13: Customer Relationship | D13: CRM Executive | E13: Divya Shree | F13: 2023-08-22 | G13: Permanent | H13: Valasaravakkam | I13: 9840012354 | J13: anitha.r@dealer.com | K13: 1997-06-09 | L13: =DATEDIF(F13,TODAY(),"y")&" yrs "&DATEDIF(F13,TODAY(),"ym")&" mo" -> 2 yrs 10 mo | M13: Active | N13: 288000 | O13: 9840099010

Sheet Recruitment Tracker
A1: RECRUITMENT TRACKER
A2: Hiring funnel, time-to-hire, cost-per-hire
A3: Req ID | B3: Position | C3: Department | D3: Date Opened | E3: Source | F3: Candidate Name | G3: Screening Date | H3: Interview Date | I3: Offer Date | J3: Joining Date | K3: Time to Hire (Days) | L3: Recruitment Cost (₹) | M3: Status
A4: REQ-101 | B4: Sales Executive | C4: Sales | D4: 2026-05-01 | E4: Naukri | F4: Karthik Raja | G4: 2026-05-04 | H4: 2026-05-10 | I4: 2026-05-14 | J4: 2026-06-01 | K4: =IF(J4<>"",J4-D4,"") -> 31 | L4: 4500 | M4: Joined
A5: REQ-102 | B5: Service Technician | C5: Service | D5: 2026-05-10 | E5: Referral | F5: Bala Murugan | G5: 2026-05-12 | H5: 2026-05-18 | K5: =IF(J5<>"",J5-D5,"") | L5: 1500 | M5: Interview Stage
A6: REQ-103 | B6: Front Office Executive | C6: Customer Relationship | D6: 2026-05-15 | E6: LinkedIn | F6: Meena S | G6: 2026-05-20 | K6: =IF(J6<>"",J6-D6,"") | L6: 3200 | M6: Screening
A7: REQ-104 | B7: Parts Executive | C7: Spare Parts | D7: 2026-04-20 | E7: Indeed | F7: Vacant | K7: =IF(J7<>"",J7-D7,"") | L7: 0 | M7: Open
A9: Total Requisitions | B9: =COUNTA(A4:A7) -> 4
A10: Joined | B10: =COUNTIF(M4:M7,"Joined") -> 1
A11: Avg Time to Hire (Days) | B11: =IFERROR(AVERAGE(K4:K7),0) -> 31
A12: Avg Cost per Hire (₹) | B12: =IFERROR(SUMIF(M4:M7,"Joined",L4:L7)/COUNTIF(M4:M7,"Joined"),0) -> 0
A13: Offer Acceptance Rate | B13: =IFERROR(COUNTIF(M4:M7,"Joined")/COUNTIF(I4:I7,"<>"),0) -> 1

Sheet Attendance Tracker
A1: ATTENDANCE TRACKER — MONTHLY
A2: Auto-calculates attendance % per employee
A3: Emp ID | B3: Name | C3: Department | D3: Working Days | E3: Present | F3: Absent | G3: Late Arrivals | H3: On Leave | I3: Attendance % | J3: Remarks
A4: AE-001 | B4: Arun Kumar S | C4: Sales | D4: 26 | E4: 24 | F4: 1 | G4: 2 | H4: 1 | I4: =E4/D4 -> 0.92307692 | J4: OK
A5: AE-002 | B5: Priya Venkatesh | C5: Service | D5: 26 | E5: 25 | F5: 0 | G5: 1 | H5: 1 | I5: =E5/D5 -> 0.96153846 | J5: OK
A6: AE-003 | B6: Manikandan R | C6: Sales | D6: 26 | E6: 26 | F6: 0 | G6: 0 | H6: 0 | I6: =E6/D6 -> 1 | J6: Excellent
A7: AE-004 | B7: Suresh Babu | C7: Bodyshop | D7: 26 | E7: 22 | F7: 2 | G7: 3 | H7: 2 | I7: =E7/D7 -> 0.84615385 | J7: Review
A8: AE-005 | B8: Lakshmi Narayanan | C8: Spare Parts | D8: 26 | E8: 25 | F8: 1 | G8: 0 | H8: 0 | I8: =E8/D8 -> 0.96153846 | J8: OK

Sheet Leave Tracker
A1: LEAVE TRACKER
A2: Leave balance and utilization by employee
A3: Emp ID | B3: Name | C3: Leave Type | D3: Entitled Days | E3: Availed Days | F3: Balance Days | G3: From Date | H3: To Date | I3: Approval Status
A4: AE-001 | B4: Arun Kumar S | C4: Casual Leave | D4: 12 | E4: 3 | F4: =D4-E4 -> 9 | G4: 2026-06-10 | H4: 2026-06-11 | I4: Approved
A5: AE-002 | B5: Priya Venkatesh | C5: Sick Leave | D5: 8 | E5: 2 | F5: =D5-E5 -> 6 | G5: 2026-05-20 | H5: 2026-05-20 | I5: Approved
A6: AE-004 | B6: Suresh Babu | C6: Earned Leave | D6: 15 | E6: 5 | F6: =D6-E6 -> 10 | G6: 2026-04-15 | H6: 2026-04-18 | I6: Approved
A7: AE-007 | B7: Divya Shree | C7: Casual Leave | D7: 12 | E7: 1 | F7: =D7-E7 -> 11 | G7: 2026-06-25 | H7: 2026-06-25 | I7: Pending

Sheet Attrition Tracker
A1: ATTRITION TRACKER
A2: Exit analysis and attrition rate calculation
A3: Emp ID | B3: Name | C3: Department | D3: Designation | E3: Date of Joining | F3: Date of Exit | G3: Tenure (Months) | H3: Exit Reason | I3: Exit Type
A4: AE-009 | B4: Vignesh Kumar | C4: Technician | D4: Senior Technician | E4: 2021-01-18 | F4: 2026-05-30 | G4: =DATEDIF(E4,F4,"m") -> 64 | H4: Better Opportunity | I4: Voluntary
A6: Total Headcount (avg) | B6: =COUNTA('Employee Master'!A4:A13) -> 10
A7: Exits (period) | B7: =COUNTA(A4:A4) -> 1
A8: Attrition Rate | B8: =B7/B6 -> 0.1

Sheet Training Tracker
A1: TRAINING & DEVELOPMENT TRACKER
A2: Track training hours, coverage, and effectiveness
A3: Emp ID | B3: Name | C3: Training Program | D3: Trainer | E3: Date | F3: Duration (Hrs) | G3: Score/Feedback | H3: Status
A4: AE-001 | B4: Arun Kumar S | C4: Consultative Selling | D4: External Trainer | E4: 2026-04-12 | F4: 4 | G4: 4.5/5 | H4: Completed
A5: AE-002 | B5: Priya Venkatesh | C5: Customer Handling & CSI | D5: Rajesh N | E5: 2026-04-20 | F5: 3 | G5: 4.2/5 | H5: Completed
A6: AE-008 | B6: Karthik Raja | C6: Product Knowledge Induction | D6: Manikandan R | E6: 2026-06-05 | F6: 6 | G6: Pending | H6: In Progress
A8: Total Training Hours | B8: =SUM(F4:F6) -> 13

Sheet Vendor & Asset Tracker
A1: ADMIN: VENDOR & ASSET REGISTER
A2: AMC status, vendor scorecard, asset register
A3: Asset/Vendor ID | B3: Item/Vendor Name | C3: Category | D3: Location | E3: Purchase/Contract Date | F3: AMC Expiry Date | G3: Vendor Rating (1-5) | H3: Cost (₹) | I3: Status
A4: AST-001 | B4: Diagnostic Scanner (Bay 2) | C4: Equipment | D4: Service Bay | E4: 2023-02-10 | F4: 2026-08-10 | G4: 4 | H4: 185000 | I4: Active
A5: AST-002 | B5: Office AC Units (x6) | C5: Facility | D5: Showroom | E5: 2022-05-01 | F5: 2026-05-01 | G5: 3 | H5: 240000 | I5: Renewal Due
A6: VND-001 | B6: Housekeeping Vendor - CleanPro | C6: Housekeeping | D6: All Branches | E6: 2024-01-01 | F6: 2026-12-31 | G6: 5 | H6: 18000 | I6: Active
A7: VND-002 | B7: Security Agency - SecureGuard | C7: Security | D7: Valasaravakkam | E7: 2023-06-01 | F7: 2026-06-01 | G7: 4 | H7: 22000 | I7: Renewal Due
A8: AST-003 | B8: Company Vehicle - Delivery Van | C8: Vehicle | D8: Valasaravakkam | E8: 2021-09-15 | F8: 2026-09-15 | G8: 4 | H8: 650000 | I8: Active

Sheet HR KPI Dashboard
A1: HR KPI DASHBOARD
A2: Live metrics pulled from source sheets — refresh via Ctrl+Alt+F9
A4: Total Headcount | C4: Attrition Rate | E4: Avg Time to Hire (Days) | G4: Avg Cost per Hire (₹)
A5: =COUNTIF('Employee Master'!M4:M13,"Active") -> 9 | C5: ='Attrition Tracker'!B8 -> 0.1 | E5: ='Recruitment Tracker'!B11 -> 31 | G5: ='Recruitment Tracker'!B12 -> 0
A8: Offer Acceptance Rate | C8: Total Training Hours (MTD) | E8: Open Positions | G8: Avg Attendance %
A9: ='Recruitment Tracker'!B13 -> 1 | C9: ='Training Tracker'!B8 -> 13 | E9: =COUNTIF('Recruitment Tracker'!M4:M7,"Open") -> 1 | G9: =AVERAGE('Attendance Tracker'!I4:I8) -> 0.93846154
A13: Department | B13: Headcount
A14: Sales | B14: =COUNTIFS('Employee Master'!C4:C13,A14,'Employee Master'!M4:M13,"Active") -> 3
A15: Service | B15: =COUNTIFS('Employee Master'!C4:C13,A15,'Employee Master'!M4:M13,"Active") -> 2
A16: Bodyshop | B16: =COUNTIFS('Employee Master'!C4:C13,A16,'Employee Master'!M4:M13,"Active") -> 1
A17: Spare Parts | B17: =COUNTIFS('Employee Master'!C4:C13,A17,'Employee Master'!M4:M13,"Active") -> 1
A18: HR & Admin | B18: =COUNTIFS('Employee Master'!C4:C13,A18,'Employee Master'!M4:M13,"Active") -> 1
A19: Technician | B19: =COUNTIFS('Employee Master'!C4:C13,A19,'Employee Master'!M4:M13,"Active") -> 0
A20: Customer Relationship | B20: =COUNTIFS('Employee Master'!C4:C13,A20,'Employee Master'!M4:M13,"Active") -> 1

Sheet Management Dashboard (MRM)
A1: MONTHLY MANAGEMENT REVIEW — MRM
A2: Executive summary for CEO/COO review
A4: Metric | B4: Value
A5: Headcount (Active) | B5: ='HR KPI Dashboard'!B4 -> 0
A6: Attrition Rate | B6: ='HR KPI Dashboard'!C4 -> Attrition Rate
A7: Open Positions | B7: ='HR KPI Dashboard'!C6 -> 0
A8: Avg Attendance % | B8: ='HR KPI Dashboard'!C10 -> 0
A9: Total Training Hours | B9: ='HR KPI Dashboard'!F6 -> 0
A10: Avg Cost per Hire (₹) | B10: ='HR KPI Dashboard'!F4 -> 0
A13: Executive Notes & Action Plan
A14: 1. Risk Area: Bodyshop attendance trending low — schedule 1:1 with Suresh Babu.
A15: 2. Recruitment: 1 open position (Parts Executive) pending 40+ days — escalate sourcing channel.
A16: 3. Training: Product induction pending for new joiner Karthik Raja — complete by next review.
A17: 4. Attrition: 1 voluntary exit (Technician) this period — exit interview insights to be logged.
A18: 5. AI Recommendation: Automate attendance sync from biometric device to eliminate manual entry errors.
